odoo9_addon_medical_manufacturer-9.0.1.0.0.99.dev6-py2.7-nspkg.pth
odoo9_addon_medical_manufacturer-9.0.1.0.0.99.dev6.dist-info/DESCRIPTION.rst
odoo9_addon_medical_manufacturer-9.0.1.0.0.99.dev6.dist-info/METADATA
odoo9_addon_medical_manufacturer-9.0.1.0.0.99.dev6.dist-info/RECORD
odoo9_addon_medical_manufacturer-9.0.1.0.0.99.dev6.dist-info/WHEEL
odoo9_addon_medical_manufacturer-9.0.1.0.0.99.dev6.dist-info/metadata.json
odoo9_addon_medical_manufacturer-9.0.1.0.0.99.dev6.dist-info/namespace_packages.txt
odoo9_addon_medical_manufacturer-9.0.1.0.0.99.dev6.dist-info/top_level.txt
odoo_addons/medical_manufacturer/README.rst
odoo_addons/medical_manufacturer/__init__.py
odoo_addons/medical_manufacturer/__openerp__.py
odoo_addons/medical_manufacturer/demo/medical_manufacturer_demo.xml
odoo_addons/medical_manufacturer/i18n/es_CO.po
odoo_addons/medical_manufacturer/i18n/es_ES.po
odoo_addons/medical_manufacturer/i18n/pt_BR.po
odoo_addons/medical_manufacturer/i18n/ro.po
odoo_addons/medical_manufacturer/models/__init__.py
odoo_addons/medical_manufacturer/models/medical_manufacturer.py
odoo_addons/medical_manufacturer/models/res_partner.py
odoo_addons/medical_manufacturer/security/ir.model.access.csv
odoo_addons/medical_manufacturer/static/description/icon.png
odoo_addons/medical_manufacturer/tests/__init__.py
odoo_addons/medical_manufacturer/tests/test_medical_manufacturer.py
odoo_addons/medical_manufacturer/views/medical_manufacturer_view.xml
odoo_addons/medical_manufacturer/views/medical_menu.xml
